{"BaseModel.3f86f8af-1283-4697-bc15-fde521a1a437": {"id": "3f86f8af-1283-4697-bc15-fde521a1a437", "created_at": "2024-01-08T16:47:41.072295", "updated_at": "2024-01-08T16:47:41.072295", "name": "My First Model", "my_number": 89, "__class__": "BaseModel"}, "User.c78d06e6-3767-45dd-948d-a5ae2be520c9": {"id": "c78d06e6-3767-45dd-948d-a5ae2be520c9", "created_at": "2024-01-08T17:32:44.862515", "updated_at": "2024-01-08T17:32:44.862515", "last_name": "Nchindap", "email": "konsenj@gmail.com", "password": "mypassword", "zip_code": "00237", "city": "Yaounde", "__class__": "User"}, "Product.0531e0a4-af93-4767-89b9-4464038e0907": {"id": "0531e0a4-af93-4767-89b9-4464038e0907", "created_at": "2024-01-08T17:34:48.684740", "updated_at": "2024-01-08T17:34:48.684740", "category": "", "image": "", "tags": [], "rating": 0.0, "reviews": [], "date_added": "", "date_updated": "", "__class__": "Product"}, "User.6718bf00-2c11-4d93-b8e7-40303b7f701d": {"id": "6718bf00-2c11-4d93-b8e7-40303b7f701d", "created_at": "2024-01-08T17:41:39.322167", "updated_at": "2024-01-08T17:41:39.322167", "first_name": "Joel", "__class__": "User"}, "Product.1aff2a5e-49d1-4326-b87c-0f7c21d2516b": {"id": "1aff2a5e-49d1-4326-b87c-0f7c21d2516b", "created_at": "2024-01-08T17:51:53.126306", "updated_at": "2024-01-08T17:51:53.126306", "category": "", "image": "", "tags": [], "rating": 0.0, "reviews": [], "date_added": "", "date_updated": "", "__class__": "Product"}, "Product.73eae55b-a4a5-4e8e-a637-5dc9af888475": {"id": "73eae55b-a4a5-4e8e-a637-5dc9af888475", "created_at": "2024-01-08T17:55:48.533547", "updated_at": "2024-01-08T17:55:48.533547", "category": "", "image": "", "tags": [], "rating": 0.0, "reviews": [], "date_added": "", "date_updated": "", "__class__": "Product"}, "Product.ecefc456-55f1-4c28-8adc-af2b97fc90e2": {"id": "ecefc456-55f1-4c28-8adc-af2b97fc90e2", "created_at": "2024-01-08T17:58:04.315841", "updated_at": "2024-01-08T17:58:04.315841", "name": "Simply Apple 100% Juice", "description": "Sweet and refreshing apple juice made with 100% pressed apples. No added sugars or preservatives.", "price": 2.49, "category": "Beverages", "tags": ["a", "p", "p", "l", "e", " ", "j", "u", "i", "c", "e", ",", "1", "0", "0", "%", " ", "j", "u", "i", "c", "e", ",", "n", "o", "n", "-", "G", "M", "O", ",", "v", "e", "g", "a", "n", ",", "k", "o", "s", "h", "e", "r"], "image": "", "rating": 0.0, "reviews": [], "date_added": "", "date_updated": "", "__class__": "Product"}, "User.7962dd52-b0aa-474a-8e76-0f66a47e1273": {"id": "7962dd52-b0aa-474a-8e76-0f66a47e1273", "created_at": "2024-01-09T17:40:30.463615", "updated_at": "2024-01-09T17:40:30.506101", "email": "konsenj@gmsil.com", "password": "mypass", "first_name": "Joel", "last_name": "Nchindap", "__class__": "User"}, "Product.4970a3c3-6a38-4182-8b1a-a1be48e3d8f1": {"id": "4970a3c3-6a38-4182-8b1a-a1be48e3d8f1", "created_at": "2024-01-09T18:06:58.432250", "updated_at": "2024-01-09T18:06:58.432250", "category": "", "image": "", "tags": [], "rating": 0.0, "reviews": [], "date_added": "", "date_updated": "", "__class__": "Product"}, "Cart.a5cfea2a-fab0-48cc-8942-855c0bf0cd5b": {"id": "a5cfea2a-fab0-48cc-8942-855c0bf0cd5b", "created_at": "2024-01-09T18:16:24.177289", "updated_at": "2024-01-09T18:16:24.177289", "__class__": "Cart"}, "Cart.83c4ac18-ecf5-46cc-a346-e1a3b2f14060": {"id": "83c4ac18-ecf5-46cc-a346-e1a3b2f14060", "created_at": "2024-01-09T18:24:50.309672", "updated_at": "2024-01-09T18:24:50.309672", "__class__": "Cart"}, "CartItem.aad771de-32f2-4225-ab02-32bee44fd16a": {"id": "aad771de-32f2-4225-ab02-32bee44fd16a", "created_at": "2024-01-09T18:25:40.357624", "updated_at": "2024-01-09T18:25:40.357624", "cart_id": "83c4ac18-ecf5-46cc-a346-e1a3b2f14060", "product_id": "ecefc456-55f1-4c28-8adc-af2b97fc90e2", "quantity": 5, "__class__": "CartItem"}, "Payment.992b2da3-91ef-4e2b-afd8-23fc651984f5": {"id": "992b2da3-91ef-4e2b-afd8-23fc651984f5", "created_at": "2024-01-11T04:47:27.755550", "updated_at": "2024-01-11T04:47:27.786306", "__class__": "Payment", "user_id": "", "cart_id": "", "payment_method": "", "payment_date": "", "payment_status": "", "transaction_id": ""}}